CHANGES.txt
MANIFEST.in
README.md
requirements-dev.txt
requirements.txt
setup.py
django_styleguide.egg-info/PKG-INFO
django_styleguide.egg-info/SOURCES.txt
django_styleguide.egg-info/dependency_links.txt
django_styleguide.egg-info/not-zip-safe
django_styleguide.egg-info/requires.txt
django_styleguide.egg-info/top_level.txt
styleguide/__init__.py
styleguide/factories.py
styleguide/models.py
styleguide/test.py
styleguide/urls.py
styleguide/utils.py
styleguide/views.py
styleguide/templates/styleguide/index.html
styleguide_mock/__init__.py