Metadata-Version: 1.0
Name: django-styleguide
Version: 0.1.22
Summary: Styleguide for django projects
Home-page: http://pypi.python.org/pypi/django-styleguide/
Author: Andre Farzat
Author-email: andrefarzat@gmail.com
License: LICENSE
Platform: UNKNOWN
